keycalculate/__init__.py
keycalculate-0.1.dist-info/LICENCE.txt
keycalculate-0.1.dist-info/METADATA
keycalculate-0.1.dist-info/WHEEL
keycalculate-0.1.dist-info/top_level.txt
keycalculate-0.1.dist-info/RECORD
