Metadata-Version: 2.1
Name: keycalculate
Version: 0.1
Summary: This is use to find key of specfic value
Home-page: UNKNOWN
Author: Madhu Hariesh
Author-email: madhuhariesh480@gmail.com
License: UNKNOWN
Platform: UNKNOWN
Classifier: Programming Language :: Python :: 3
Classifier: License :: OSI Approved :: MIT License
Classifier: Operating System :: OS Independent
License-File: LICENCE.txt
